CyroStack/__init__.py
CyroStack/console.py
CyroStack/request.py
CyroStack/response.py
CyroStack/router.py
CyroStack/Frontend/__init__.py
CyroStack-0.0.1.dist-info/LICENSE
CyroStack-0.0.1.dist-info/METADATA
CyroStack-0.0.1.dist-info/WHEEL
CyroStack-0.0.1.dist-info/top_level.txt
CyroStack-0.0.1.dist-info/RECORD
